setup.py
bmi_cal_omid2/__init__.py
bmi_cal_omid2/bmi_calculetor.py
bmi_cal_omid2.egg-info/PKG-INFO
bmi_cal_omid2.egg-info/SOURCES.txt
bmi_cal_omid2.egg-info/dependency_links.txt
bmi_cal_omid2.egg-info/top_level.txt
bmi_cal_omid2.egg-info/zip-safe