Metadata-Version: 1.0
Name: bmi-cal-omid2
Version: 1.1
Summary: calclutor
Home-page: UNKNOWN
Author: omid
Author-email: UNKNOWN
License: UNKNOWN
Platform: UNKNOWN
